[
    {
        "key": "group_5da60b8a123d1",
        "title": "Global Options",
        "fields": [
            {
                "key": "field_5e17609c644b3",
                "label": "Site Info",
                "name": "",
                "type": "tab",
                "instructions": "",
                "required": 0,
                "conditional_logic": 0,
                "wrapper": {
                    "width": "",
                    "class": "",
                    "id": ""
                },
                "placement": "top",
                "endpoint": 0
            },
            {
                "key": "field_5e62c9c238bf5",
                "label": "Main Logo",
                "name": "main_logo",
                "type": "image",
                "instructions": "",
                "required": 0,
                "conditional_logic": 0,
                "wrapper": {
                    "width": "",
                    "class": "",
                    "id": ""
                },
                "return_format": "array",
                "preview_size": "medium",
                "library": "all",
                "min_width": "",
                "min_height": "",
                "min_size": "",
                "max_width": "",
                "max_height": "",
                "max_size": "",
                "mime_types": ""
            },
            {
                "key": "field_5e1760a6644b4",
                "label": "Logo Light",
                "name": "logo_light",
                "type": "image",
                "instructions": "",
                "required": 0,
                "conditional_logic": 0,
                "wrapper": {
                    "width": "",
                    "class": "",
                    "id": ""
                },
                "return_format": "array",
                "preview_size": "medium",
                "library": "all",
                "min_width": "",
                "min_height": "",
                "min_size": "",
                "max_width": "",
                "max_height": "",
                "max_size": "",
                "mime_types": ""
            },
            {
                "key": "field_5e1760b2644b5",
                "label": "Logo Dark",
                "name": "logo_dark",
                "type": "image",
                "instructions": "",
                "required": 0,
                "conditional_logic": 0,
                "wrapper": {
                    "width": "",
                    "class": "",
                    "id": ""
                },
                "return_format": "array",
                "preview_size": "medium",
                "library": "all",
                "min_width": "",
                "min_height": "",
                "min_size": "",
                "max_width": "",
                "max_height": "",
                "max_size": "",
                "mime_types": ""
            },
            {
                "key": "field_5e62ca3dfc8ea",
                "label": "Contact Info",
                "name": "",
                "type": "tab",
                "instructions": "",
                "required": 0,
                "conditional_logic": 0,
                "wrapper": {
                    "width": "",
                    "class": "",
                    "id": ""
                },
                "placement": "top",
                "endpoint": 0
            },
            {
                "key": "field_5da60ce8a19c7",
                "label": "Email",
                "name": "email",
                "type": "text",
                "instructions": "",
                "required": 0,
                "conditional_logic": 0,
                "wrapper": {
                    "width": "",
                    "class": "",
                    "id": ""
                },
                "default_value": "",
                "placeholder": "",
                "prepend": "",
                "append": "",
                "maxlength": ""
            },
            {
                "key": "field_5da60ceea19c8",
                "label": "Phone",
                "name": "phone",
                "type": "text",
                "instructions": "",
                "required": 0,
                "conditional_logic": 0,
                "wrapper": {
                    "width": "",
                    "class": "",
                    "id": ""
                },
                "default_value": "",
                "placeholder": "",
                "prepend": "",
                "append": "",
                "maxlength": ""
            },
            {
                "key": "field_5e39c70a4967d",
                "label": "Address",
                "name": "address",
                "type": "textarea",
                "instructions": "",
                "required": 0,
                "conditional_logic": 0,
                "wrapper": {
                    "width": "",
                    "class": "",
                    "id": ""
                },
                "default_value": "",
                "placeholder": "",
                "maxlength": "",
                "rows": "",
                "new_lines": "br"
            },
            {
                "key": "field_5e39c74cc816f",
                "label": "Location Map URL",
                "name": "location_map_url",
                "type": "text",
                "instructions": "",
                "required": 0,
                "conditional_logic": 0,
                "wrapper": {
                    "width": "",
                    "class": "",
                    "id": ""
                },
                "default_value": "",
                "placeholder": "",
                "prepend": "",
                "append": "",
                "maxlength": ""
            },
            {
                "key": "field_5e39c75fc8170",
                "label": "Directions Link",
                "name": "directions_link",
                "type": "text",
                "instructions": "",
                "required": 0,
                "conditional_logic": 0,
                "wrapper": {
                    "width": "",
                    "class": "",
                    "id": ""
                },
                "default_value": "",
                "placeholder": "",
                "prepend": "",
                "append": "",
                "maxlength": ""
            },
            {
                "key": "field_5da60b8f3098f",
                "label": "Social",
                "name": "",
                "type": "tab",
                "instructions": "",
                "required": 0,
                "conditional_logic": 0,
                "wrapper": {
                    "width": "",
                    "class": "",
                    "id": ""
                },
                "placement": "top",
                "endpoint": 0
            },
            {
                "key": "field_5e39a3552a42a",
                "label": "Social Handle",
                "name": "social_handle",
                "type": "text",
                "instructions": "",
                "required": 0,
                "conditional_logic": 0,
                "wrapper": {
                    "width": "",
                    "class": "",
                    "id": ""
                },
                "default_value": "",
                "placeholder": "",
                "prepend": "",
                "append": "",
                "maxlength": ""
            },
            {
                "key": "field_5da60b9630990",
                "label": "Social Links",
                "name": "social_links",
                "type": "group",
                "instructions": "",
                "required": 0,
                "conditional_logic": 0,
                "wrapper": {
                    "width": "",
                    "class": "",
                    "id": ""
                },
                "layout": "block",
                "sub_fields": [
                    {
                        "key": "field_5e3992dc27caf",
                        "label": "Facebook",
                        "name": "facebook",
                        "type": "text",
                        "instructions": "",
                        "required": 0,
                        "conditional_logic": 0,
                        "wrapper": {
                            "width": "",
                            "class": "",
                            "id": ""
                        },
                        "default_value": "",
                        "placeholder": "",
                        "prepend": "",
                        "append": "",
                        "maxlength": ""
                    },
                    {
                        "key": "field_5da60bab30992",
                        "label": "Platform URL",
                        "name": "platform_url",
                        "type": "text",
                        "instructions": "",
                        "required": 0,
                        "conditional_logic": 0,
                        "wrapper": {
                            "width": "",
                            "class": "",
                            "id": ""
                        },
                        "default_value": "",
                        "placeholder": "",
                        "prepend": "",
                        "append": "",
                        "maxlength": ""
                    },
                    {
                        "key": "field_5e3992e127cb0",
                        "label": "Twitter",
                        "name": "twitter",
                        "type": "text",
                        "instructions": "",
                        "required": 0,
                        "conditional_logic": 0,
                        "wrapper": {
                            "width": "",
                            "class": "",
                            "id": ""
                        },
                        "default_value": "",
                        "placeholder": "",
                        "prepend": "",
                        "append": "",
                        "maxlength": ""
                    },
                    {
                        "key": "field_5e39933427cb1",
                        "label": "Instagram",
                        "name": "instagram",
                        "type": "text",
                        "instructions": "",
                        "required": 0,
                        "conditional_logic": 0,
                        "wrapper": {
                            "width": "",
                            "class": "",
                            "id": ""
                        },
                        "default_value": "",
                        "placeholder": "",
                        "prepend": "",
                        "append": "",
                        "maxlength": ""
                    },
                    {
                        "key": "field_5e39933a27cb2",
                        "label": "LinkedIn",
                        "name": "linkedin",
                        "type": "text",
                        "instructions": "",
                        "required": 0,
                        "conditional_logic": 0,
                        "wrapper": {
                            "width": "",
                            "class": "",
                            "id": ""
                        },
                        "default_value": "",
                        "placeholder": "",
                        "prepend": "",
                        "append": "",
                        "maxlength": ""
                    },
                    {
                        "key": "field_5e39934a27cb3",
                        "label": "Google",
                        "name": "google",
                        "type": "text",
                        "instructions": "",
                        "required": 0,
                        "conditional_logic": 0,
                        "wrapper": {
                            "width": "",
                            "class": "",
                            "id": ""
                        },
                        "default_value": "",
                        "placeholder": "",
                        "prepend": "",
                        "append": "",
                        "maxlength": ""
                    },
                    {
                        "key": "field_5e39934f27cb4",
                        "label": "Pinterest",
                        "name": "pinterest",
                        "type": "text",
                        "instructions": "",
                        "required": 0,
                        "conditional_logic": 0,
                        "wrapper": {
                            "width": "",
                            "class": "",
                            "id": ""
                        },
                        "default_value": "",
                        "placeholder": "",
                        "prepend": "",
                        "append": "",
                        "maxlength": ""
                    },
                    {
                        "key": "field_5e39938041685",
                        "label": "Youtube",
                        "name": "youtube",
                        "type": "text",
                        "instructions": "",
                        "required": 0,
                        "conditional_logic": 0,
                        "wrapper": {
                            "width": "",
                            "class": "",
                            "id": ""
                        },
                        "default_value": "",
                        "placeholder": "",
                        "prepend": "",
                        "append": "",
                        "maxlength": ""
                    }
                ]
            },
            {
                "key": "field_5e3056f71c14f",
                "label": "Single Post",
                "name": "",
                "type": "tab",
                "instructions": "",
                "required": 0,
                "conditional_logic": 0,
                "wrapper": {
                    "width": "",
                    "class": "",
                    "id": ""
                },
                "placement": "top",
                "endpoint": 0
            },
            {
                "key": "field_5e3056fe1c150",
                "label": "Post Placeholder Image",
                "name": "post_placeholder_image",
                "type": "image",
                "instructions": "",
                "required": 0,
                "conditional_logic": 0,
                "wrapper": {
                    "width": "",
                    "class": "",
                    "id": ""
                },
                "return_format": "array",
                "preview_size": "medium",
                "library": "all",
                "min_width": "",
                "min_height": "",
                "min_size": "",
                "max_width": "",
                "max_height": "",
                "max_size": "",
                "mime_types": ""
            },
            {
                "key": "field_5e38fc1d39dc3",
                "label": "Sidebar Ad Image",
                "name": "sidebar_ad_image",
                "type": "image",
                "instructions": "",
                "required": 0,
                "conditional_logic": 0,
                "wrapper": {
                    "width": "",
                    "class": "",
                    "id": ""
                },
                "return_format": "array",
                "preview_size": "medium",
                "library": "all",
                "min_width": "",
                "min_height": "",
                "min_size": "",
                "max_width": "",
                "max_height": "",
                "max_size": "",
                "mime_types": ""
            },
            {
                "key": "field_5e38fc3a39dc4",
                "label": "Sidebar Ad Link",
                "name": "sidebar_ad_link",
                "type": "link",
                "instructions": "",
                "required": 0,
                "conditional_logic": 0,
                "wrapper": {
                    "width": "",
                    "class": "",
                    "id": ""
                },
                "return_format": "array"
            }
        ],
        "location": [
            [
                {
                    "param": "options_page",
                    "operator": "==",
                    "value": "acf-options"
                }
            ]
        ],
        "menu_order": 0,
        "position": "normal",
        "style": "default",
        "label_placement": "top",
        "instruction_placement": "label",
        "hide_on_screen": "",
        "active": true,
        "description": ""
    },
    {
        "key": "group_5e1d25961b177",
        "title": "Header",
        "fields": [
            {
                "key": "field_5e2898f3fb239",
                "label": "Header Options",
                "name": "",
                "type": "tab",
                "instructions": "",
                "required": 0,
                "conditional_logic": 0,
                "wrapper": {
                    "width": "",
                    "class": "",
                    "id": ""
                },
                "placement": "top",
                "endpoint": 0
            },
            {
                "key": "field_5e1d25adc7e27",
                "label": "Header Color",
                "name": "header_color",
                "type": "select",
                "instructions": "",
                "required": 0,
                "conditional_logic": 0,
                "wrapper": {
                    "width": "",
                    "class": "",
                    "id": ""
                },
                "choices": {
                    "light": "Light",
                    "dark": "Dark"
                },
                "default_value": [
                    "light"
                ],
                "allow_null": 0,
                "multiple": 0,
                "ui": 0,
                "return_format": "value",
                "ajax": 0,
                "placeholder": ""
            },
            {
                "key": "field_5e1f8d2eb04c2",
                "label": "Header Type",
                "name": "header_type",
                "type": "select",
                "instructions": "",
                "required": 0,
                "conditional_logic": 0,
                "wrapper": {
                    "width": "",
                    "class": "",
                    "id": ""
                },
                "choices": {
                    "primary": "Primary",
                    "secondary": "Secondary"
                },
                "default_value": [],
                "allow_null": 0,
                "multiple": 0,
                "ui": 0,
                "return_format": "value",
                "ajax": 0,
                "placeholder": ""
            }
        ],
        "location": [
            [
                {
                    "param": "post_type",
                    "operator": "==",
                    "value": "post"
                }
            ],
            [
                {
                    "param": "post_type",
                    "operator": "==",
                    "value": "page"
                }
            ],
            [
                {
                    "param": "post_type",
                    "operator": "==",
                    "value": "post"
                }
            ],
            [
                {
                    "param": "post_type",
                    "operator": "==",
                    "value": "testimonials"
                }
            ],
            [
                {
                    "param": "post_type",
                    "operator": "==",
                    "value": "locations"
                }
            ]
        ],
        "menu_order": 0,
        "position": "acf_after_title",
        "style": "default",
        "label_placement": "top",
        "instruction_placement": "label",
        "hide_on_screen": "",
        "active": true,
        "description": ""
    },
    {
        "key": "group_5d84eeee40903",
        "title": "Hero",
        "fields": [
            {
                "key": "field_5e2899059ac9c",
                "label": "Hero General Options",
                "name": "",
                "type": "tab",
                "instructions": "",
                "required": 0,
                "conditional_logic": 0,
                "wrapper": {
                    "width": "",
                    "class": "",
                    "id": ""
                },
                "placement": "top",
                "endpoint": 0
            },
            {
                "key": "field_5e1d22a3f5d8e",
                "label": "Hero Color",
                "name": "hero_color",
                "type": "select",
                "instructions": "",
                "required": 0,
                "conditional_logic": 0,
                "wrapper": {
                    "width": "",
                    "class": "",
                    "id": ""
                },
                "choices": {
                    "light": "Light",
                    "dark": "Dark",
                    "bottom_gradient": "Bottom Gradient"
                },
                "default_value": [],
                "allow_null": 0,
                "multiple": 0,
                "ui": 0,
                "return_format": "value",
                "ajax": 0,
                "placeholder": ""
            },
            {
                "key": "field_5e1d28f2667dc",
                "label": "Show Address Form",
                "name": "show_address_form",
                "type": "select",
                "instructions": "",
                "required": 0,
                "conditional_logic": 0,
                "wrapper": {
                    "width": "",
                    "class": "",
                    "id": ""
                },
                "choices": {
                    "no": "No",
                    "yes": "Yes"
                },
                "default_value": [
                    "no"
                ],
                "allow_null": 0,
                "multiple": 0,
                "ui": 0,
                "return_format": "value",
                "ajax": 0,
                "placeholder": ""
            },
            {
                "key": "field_5e1d2902667dd",
                "label": "Show Call Button",
                "name": "show_call_button",
                "type": "select",
                "instructions": "",
                "required": 0,
                "conditional_logic": 0,
                "wrapper": {
                    "width": "",
                    "class": "",
                    "id": ""
                },
                "choices": {
                    "no": "No",
                    "yes": "Yes"
                },
                "default_value": [],
                "allow_null": 0,
                "multiple": 0,
                "ui": 0,
                "return_format": "value",
                "ajax": 0,
                "placeholder": ""
            },
            {
                "key": "field_5e28994bcc051",
                "label": "Hero Image Settings",
                "name": "",
                "type": "tab",
                "instructions": "",
                "required": 0,
                "conditional_logic": 0,
                "wrapper": {
                    "width": "",
                    "class": "",
                    "id": ""
                },
                "placement": "top",
                "endpoint": 0
            },
            {
                "key": "field_5d84ef938b564",
                "label": "Hero Image",
                "name": "hero_image",
                "type": "image",
                "instructions": "",
                "required": 0,
                "conditional_logic": 0,
                "wrapper": {
                    "width": "",
                    "class": "",
                    "id": ""
                },
                "return_format": "array",
                "preview_size": "medium",
                "library": "all",
                "min_width": "",
                "min_height": "",
                "min_size": "",
                "max_width": "",
                "max_height": "",
                "max_size": "",
                "mime_types": ""
            },
            {
                "key": "field_5d84f04d8b568",
                "label": "Image Opacity",
                "name": "hero_overlay_opacity",
                "type": "range",
                "instructions": "",
                "required": 0,
                "conditional_logic": 0,
                "wrapper": {
                    "width": "",
                    "class": "",
                    "id": ""
                },
                "default_value": 100,
                "min": "",
                "max": 100,
                "step": "",
                "prepend": "",
                "append": ""
            },
            {
                "key": "field_5e289954cc052",
                "label": "Hero Content",
                "name": "",
                "type": "tab",
                "instructions": "",
                "required": 0,
                "conditional_logic": 0,
                "wrapper": {
                    "width": "",
                    "class": "",
                    "id": ""
                },
                "placement": "top",
                "endpoint": 0
            },
            {
                "key": "field_5e1f352af5391",
                "label": "Hero Pre-Title",
                "name": "hero_pretitle",
                "type": "text",
                "instructions": "",
                "required": 0,
                "conditional_logic": 0,
                "wrapper": {
                    "width": "",
                    "class": "",
                    "id": ""
                },
                "default_value": "",
                "placeholder": "",
                "prepend": "",
                "append": "",
                "maxlength": ""
            },
            {
                "key": "field_5d84efb78b566",
                "label": "Hero Title",
                "name": "hero_title",
                "type": "text",
                "instructions": "",
                "required": 0,
                "conditional_logic": 0,
                "wrapper": {
                    "width": "",
                    "class": "",
                    "id": ""
                },
                "default_value": "",
                "placeholder": "",
                "prepend": "",
                "append": "",
                "maxlength": ""
            },
            {
                "key": "field_5d84f0488b567",
                "label": "Hero Subtitle",
                "name": "hero_subtitle",
                "type": "text",
                "instructions": "",
                "required": 0,
                "conditional_logic": 0,
                "wrapper": {
                    "width": "",
                    "class": "",
                    "id": ""
                },
                "default_value": "",
                "placeholder": "",
                "prepend": "",
                "append": "",
                "maxlength": ""
            },
            {
                "key": "field_5d84f05e8b569",
                "label": "Hero CTA",
                "name": "hero_cta",
                "type": "group",
                "instructions": "",
                "required": 0,
                "conditional_logic": 0,
                "wrapper": {
                    "width": "",
                    "class": "",
                    "id": ""
                },
                "layout": "block",
                "sub_fields": [
                    {
                        "key": "field_5d84f06e8b56b",
                        "label": "Link URL",
                        "name": "link_url",
                        "type": "link",
                        "instructions": "",
                        "required": 0,
                        "conditional_logic": 0,
                        "wrapper": {
                            "width": "",
                            "class": "",
                            "id": ""
                        },
                        "return_format": "array"
                    },
                    {
                        "key": "field_5d84f0768b56c",
                        "label": "Link Text",
                        "name": "link_text",
                        "type": "text",
                        "instructions": "",
                        "required": 0,
                        "conditional_logic": 0,
                        "wrapper": {
                            "width": "",
                            "class": "",
                            "id": ""
                        },
                        "default_value": "",
                        "placeholder": "",
                        "prepend": "",
                        "append": "",
                        "maxlength": ""
                    }
                ]
            },
            {
                "key": "field_5e1f61a1a76c9",
                "label": "Hero Content",
                "name": "hero_content",
                "type": "textarea",
                "instructions": "",
                "required": 0,
                "conditional_logic": 0,
                "wrapper": {
                    "width": "",
                    "class": "",
                    "id": ""
                },
                "default_value": "",
                "placeholder": "",
                "maxlength": "",
                "rows": "",
                "new_lines": ""
            }
        ],
        "location": [
            [
                {
                    "param": "post_type",
                    "operator": "==",
                    "value": "page"
                }
            ],
            [
                {
                    "param": "post_type",
                    "operator": "==",
                    "value": "locations"
                }
            ]
        ],
        "menu_order": 0,
        "position": "acf_after_title",
        "style": "default",
        "label_placement": "top",
        "instruction_placement": "label",
        "hide_on_screen": "",
        "active": true,
        "description": ""
    },
    {
        "key": "group_5e30421529222",
        "title": "Single Post",
        "fields": [
            {
                "key": "field_5e30421883bff",
                "label": "Post Image",
                "name": "post_image",
                "type": "image",
                "instructions": "",
                "required": 0,
                "conditional_logic": 0,
                "wrapper": {
                    "width": "",
                    "class": "",
                    "id": ""
                },
                "return_format": "array",
                "preview_size": "medium",
                "library": "all",
                "min_width": "",
                "min_height": "",
                "min_size": "",
                "max_width": "",
                "max_height": "",
                "max_size": "",
                "mime_types": ""
            }
        ],
        "location": [
            [
                {
                    "param": "post_type",
                    "operator": "==",
                    "value": "post"
                }
            ]
        ],
        "menu_order": 0,
        "position": "acf_after_title",
        "style": "default",
        "label_placement": "top",
        "instruction_placement": "label",
        "hide_on_screen": "",
        "active": true,
        "description": ""
    },
    {
        "key": "group_5e2e002d1d95c",
        "title": "Testimonials",
        "fields": [
            {
                "key": "field_5e2e00612c1d3",
                "label": "Client Name",
                "name": "client_name",
                "type": "text",
                "instructions": "",
                "required": 0,
                "conditional_logic": 0,
                "wrapper": {
                    "width": "",
                    "class": "",
                    "id": ""
                },
                "default_value": "",
                "placeholder": "",
                "prepend": "",
                "append": "",
                "maxlength": ""
            },
            {
                "key": "field_5e2e005a2c1d2",
                "label": "Client Location",
                "name": "client_location",
                "type": "text",
                "instructions": "",
                "required": 0,
                "conditional_logic": 0,
                "wrapper": {
                    "width": "",
                    "class": "",
                    "id": ""
                },
                "default_value": "",
                "placeholder": "",
                "prepend": "",
                "append": "",
                "maxlength": ""
            }
        ],
        "location": [
            [
                {
                    "param": "post_type",
                    "operator": "==",
                    "value": "testimonials"
                }
            ]
        ],
        "menu_order": 0,
        "position": "acf_after_title",
        "style": "default",
        "label_placement": "top",
        "instruction_placement": "label",
        "hide_on_screen": "",
        "active": true,
        "description": ""
    }
]